[
  {
    "Team": "D.K’s Dying Minions",
    "NPG": 9,
    "RPA": 14,
    "DM": 119,
    "The Barkley Brawlers Win DM": 0,
    "D.K’s Dying Minions Win DM": 138,
    "NPG_color": "#bc293d",
    "RPA_color": "#bc293d",
    "DM_color": "#bc293d",
    "The Barkley Brawlers Win DM_color": "#227740",
    "D.K’s Dying Minions Win DM_color": "#bc293d"
  },
  {
    "Team": "The Barkley Brawlers",
    "NPG": 9,
    "RPA": 14,
    "DM": 119,
    "The Barkley Brawlers Win DM": 125,
    "D.K’s Dying Minions Win DM": 12,
    "NPG_color": "#bc293d",
    "RPA_color": "#bc293d",
    "DM_color": "#bc293d",
    "The Barkley Brawlers Win DM_color": "#bc293d",
    "D.K’s Dying Minions Win DM_color": "#4c8d5d"
  },
  {
    "Team": "Lord of the Littles",
    "NPG": 10,
    "RPA": 12,
    "DM": 62,
    "The Barkley Brawlers Win DM": 25,
    "D.K’s Dying Minions Win DM": 100,
    "NPG_color": "#f1bcb9",
    "RPA_color": "#eaa5a3",
    "DM_color": "#dbe8dd",
    "The Barkley Brawlers Win DM_color": "#7cab86",
    "D.K’s Dying Minions Win DM_color": "#eaa5a3"
  },
  {
    "Team": "Uncle Rico Went Pro",
    "NPG": 10,
    "RPA": 9,
    "DM": 56,
    "The Barkley Brawlers Win DM": 112,
    "D.K’s Dying Minions Win DM": 0,
    "NPG_color": "#f1bcb9",
    "RPA_color": "#9fc2a6",
    "DM_color": "#c3d8c6",
    "The Barkley Brawlers Win DM_color": "#d16163",
    "D.K’s Dying Minions Win DM_color": "#227740"
  },
  {
    "Team": "Bye Week Curious",
    "NPG": 11,
    "RPA": 12,
    "DM": 44,
    "The Barkley Brawlers Win DM": 0,
    "D.K’s Dying Minions Win DM": 88,
    "NPG_color": "#b7d1bb",
    "RPA_color": "#eaa5a3",
    "DM_color": "#94ba9b",
    "The Barkley Brawlers Win DM_color": "#227740",
    "D.K’s Dying Minions Win DM_color": "#f4c7c4"
  },
  {
    "Team": "Singing Like Mariah Terry",
    "NPG": 11,
    "RPA": 12,
    "DM": 44,
    "The Barkley Brawlers Win DM": 75,
    "D.K’s Dying Minions Win DM": 12,
    "NPG_color": "#b7d1bb",
    "RPA_color": "#eaa5a3",
    "DM_color": "#94ba9b",
    "The Barkley Brawlers Win DM_color": "#f7d2d0",
    "D.K’s Dying Minions Win DM_color": "#4c8d5d"
  },
  {
    "Team": "Costco Guys",
    "NPG": 11,
    "RPA": 11,
    "DM": 38,
    "The Barkley Brawlers Win DM": 0,
    "D.K’s Dying Minions Win DM": 75,
    "NPG_color": "#b7d1bb",
    "RPA_color": "#f9dddc",
    "DM_color": "#7cab86",
    "The Barkley Brawlers Win DM_color": "#227740",
    "D.K’s Dying Minions Win DM_color": "#fbe8e7"
  },
  {
    "Team": "WalterPickens",
    "NPG": 11,
    "RPA": 8,
    "DM": 31,
    "The Barkley Brawlers Win DM": 62,
    "D.K’s Dying Minions Win DM": 0,
    "NPG_color": "#b7d1bb",
    "RPA_color": "#649c71",
    "DM_color": "#589567",
    "The Barkley Brawlers Win DM_color": "#f3f7f3",
    "D.K’s Dying Minions Win DM_color": "#227740"
  },
  {
    "Team": "First Down Syndrome",
    "NPG": 12,
    "RPA": 10,
    "DM": 25,
    "The Barkley Brawlers Win DM": 25,
    "D.K’s Dying Minions Win DM": 25,
    "NPG_color": "#227740",
    "RPA_color": "#dbe8dd",
    "DM_color": "#3f8653",
    "The Barkley Brawlers Win DM_color": "#7cab86",
    "D.K’s Dying Minions Win DM_color": "#70a37c"
  },
  {
    "Team": "One and six",
    "NPG": 12,
    "RPA": 10,
    "DM": 25,
    "The Barkley Brawlers Win DM": 0,
    "D.K’s Dying Minions Win DM": 50,
    "NPG_color": "#227740",
    "RPA_color": "#dbe8dd",
    "DM_color": "#3f8653",
    "The Barkley Brawlers Win DM_color": "#227740",
    "D.K’s Dying Minions Win DM_color": "#c3d8c6"
  },
  {
    "Team": "BBCU",
    "NPG": 12,
    "RPA": 7,
    "DM": 19,
    "The Barkley Brawlers Win DM": 38,
    "D.K’s Dying Minions Win DM": 0,
    "NPG_color": "#227740",
    "RPA_color": "#227740",
    "DM_color": "#227740",
    "The Barkley Brawlers Win DM_color": "#abc9b1",
    "D.K’s Dying Minions Win DM_color": "#227740"
  },
  {
    "Team": "Super Ja'Marrio Bros.",
    "NPG": 12,
    "RPA": 7,
    "DM": 19,
    "The Barkley Brawlers Win DM": 38,
    "D.K’s Dying Minions Win DM": 0,
    "NPG_color": "#227740",
    "RPA_color": "#227740",
    "DM_color": "#227740",
    "The Barkley Brawlers Win DM_color": "#abc9b1",
    "D.K’s Dying Minions Win DM_color": "#227740"
  }
]
